LICENSE
README.md
setup.py
CVE_2015_1635.egg-info/PKG-INFO
CVE_2015_1635.egg-info/SOURCES.txt
CVE_2015_1635.egg-info/dependency_links.txt
CVE_2015_1635.egg-info/entry_points.txt
CVE_2015_1635.egg-info/requires.txt
CVE_2015_1635.egg-info/top_level.txt
cve20151635/__init__.py
cve20151635/main.py
cve20151635/includes/__init__.py
cve20151635/includes/bot.py
cve20151635/includes/filereader.py
cve20151635/includes/scan.py
cve20151635/includes/writefile.py
cve20151635/utils/__init__.py
cve20151635/utils/configure.py
cve20151635/utils/const.py
cve20151635/utils/helpers.py
cve20151635/utils/status.py